LICENSE
LICENSE_JQUERY
LICENSE_JQUERYUI
LICENSE_bootstrap
MANIFEST.in
README.rst
setup.py
django_easydata.egg-info/PKG-INFO
django_easydata.egg-info/SOURCES.txt
django_easydata.egg-info/dependency_links.txt
django_easydata.egg-info/requires.txt
django_easydata.egg-info/top_level.txt
docs/api.pdf
docs/memoria.pdf
easydata/__init__.py
easydata/tests.py
easydata/urls.py
easydata/utils.py
easydata/decorators/__init__.py
easydata/decorators/decorators.py
easydata/forms/__init__.py
easydata/forms/forms/__init__.py
easydata/forms/forms/d2rqform.py
easydata/forms/modelforms/__init__.py
easydata/forms/modelforms/editnamespace.py
easydata/forms/modelforms/fieldpropiedad.py
easydata/forms/modelforms/modeloentidad.py
easydata/forms/modelforms/newnamespace.py
easydata/forms/modelforms/visibilityfields.py
easydata/forms/modelforms/visibilitymodels.py
easydata/locale/en/LC_MESSAGES/django.mo
easydata/locale/en/LC_MESSAGES/django.po
easydata/locale/es/LC_MESSAGES/django.mo
easydata/locale/es/LC_MESSAGES/django.po
easydata/locale/l/LC_MESSAGES/django.mo
easydata/locale/l/LC_MESSAGES/django.po
easydata/management/__init__.py
easydata/management/commands/__init__.py
easydata/management/commands/easydata_d2rq.py
easydata/management/commands/loadmodels.py
easydata/models/__init__.py
easydata/models/entidad.py
easydata/models/field.py
easydata/models/modelo.py
easydata/models/namespace.py
easydata/models/propiedad.py
easydata/parsing/__init__.py
easydata/parsing/parseador.py
easydata/parsing/parserfactory.py
easydata/parsing/rdf_parser.py
easydata/parsing/registers.py
easydata/parsing/schema_parser.py
easydata/static/easydata/css/bootstrap.css
easydata/static/easydata/css/jquery-ui-1.10.3.custom.min.css
easydata/static/easydata/css/style.css
easydata/static/easydata/img/fabicon.png
easydata/static/easydata/img/linked_logo.png
easydata/static/easydata/img/logo_final.png
easydata/static/easydata/img/logo_web.png
easydata/static/easydata/img/ui-theme/animated-overlay.gif
easydata/static/easydata/img/ui-theme/ui-bg_flat_0_aaaaaa_40x100.png
easydata/static/easydata/img/ui-theme/ui-bg_flat_55_fbec88_40x100.png
easydata/static/easydata/img/ui-theme/ui-bg_glass_75_d0e5f5_1x400.png
