Metadata-Version: 1.1
Name: django-easydata
Version: 0.1
Summary: A Django app to publish your project data using ontologies.
Home-page: UNKNOWN
Author: Jose Manuel Llerena
Author-email: jose.llerecarmo@alum.uca.es
License: GNU License
Keywords: ontology,rdf,rdfa,semantic web,django,microdata
Platform: UNKNOWN
Classifier: Environment :: Web Environment
Classifier: Framework :: Django
Classifier: Operating System :: OS Independent
Classifier: Programming Language :: Python :: 2
Classifier: Topic :: Internet :: WWW/HTTP
Classifier: Topic :: Internet :: WWW/HTTP :: Dynamic Content
